{"cameraMode":{"drawMode":0,"name":"Shaded","section":"Shading Mode"},"sceneLighting":true,"audioPlay":false,"sceneViewState":{"showFog":true,"showMaterialUpdate":false,"showSkybox":true,"showFlares":true,"showImageEffects":true,"showParticleSystems":true},"in2DMode":false,"pivot":{"x":-219.25888061523438,"y":93.13695526123047,"z":128.10519409179688},"rotation":{"x":-0.21287299692630769,"y":0.4899863004684448,"z":-0.12475399672985077,"w":-0.8360862731933594},"size":42.553768157958987,"orthographic":false}